{"version":3,"kind":"Article","sha256":"78dd8548968a105f48e573aaca037b5c0b6a947cff8c8e21ea109aefd9866f63","slug":"index","location":"/index.md","dependencies":[],"frontmatter":{"title":"Proyecto No 4000000452 (Interacciones del Flujo de Humedad Atmosférica y el Ciclo Diurno de la Lluvia en los Andes Colombianos a partir del Reanálisis ERA-5 (4D-Var))","exports":[{"format":"md","filename":"index.md","url":"/jupyterbook_MA/build/index-9c6716a467ecd691694c72c0742c78ed.md"}]},"mdast":{"type":"root","children":[{"type":"block","children":[{"type":"heading","depth":2,"position":{"start":{"line":6,"column":1},"end":{"line":6,"column":1}},"children":[{"type":"text","value":"Content","position":{"start":{"line":6,"column":1},"end":{"line":6,"column":1}},"key":"qTPocJX6fA"}],"identifier":"content","label":"Content","html_id":"content","implicit":true,"key":"aPZUwHKipY"},{"type":"heading","depth":3,"position":{"start":{"line":8,"column":1},"end":{"line":8,"column":1}},"children":[{"type":"text","value":"Capitulos: Tabla de contenido","position":{"start":{"line":8,"column":1},"end":{"line":8,"column":1}},"key":"I4uEVXedyV"}],"identifier":"capitulos-tabla-de-contenido","label":"Capitulos: Tabla de contenido","html_id":"capitulos-tabla-de-contenido","implicit":true,"key":"lQpD2IwQkX"},{"type":"list","ordered":false,"spread":false,"position":{"start":{"line":9,"column":1},"end":{"line":10,"column":1}},"children":[{"type":"listItem","spread":true,"position":{"start":{"line":9,"column":1},"end":{"line":9,"column":1}},"children":[{"type":"paragraph","children":[{"type":"link","url":"/capitulo-1-actividad-1","position":{"start":{"line":9,"column":1},"end":{"line":9,"column":1}},"children":[{"type":"text","value":"Capitulo 1: Estado del Arte (Algoritmos Implementados)","position":{"start":{"line":9,"column":1},"end":{"line":9,"column":1}},"key":"DMq365mnfW"}],"urlSource":"content/capitulo-1-actividad-1","dataUrl":"/capitulo-1-actividad-1.json","internal":true,"protocol":"file","key":"unI4aLUTzp"}],"key":"BLlJ57gtNa"}],"key":"CsBh6rJqKZ"},{"type":"listItem","spread":true,"position":{"start":{"line":10,"column":1},"end":{"line":10,"column":1}},"children":[{"type":"paragraph","children":[{"type":"link","url":"/capitulo-2-imputando-series-de-precipitacion-mensu","position":{"start":{"line":10,"column":1},"end":{"line":10,"column":1}},"children":[{"type":"text","value":"Capitulo 2: Imputando series de precipitacion mensual","position":{"start":{"line":10,"column":1},"end":{"line":10,"column":1}},"key":"H2UI83eK8w"}],"urlSource":"content/capitulo-2-imputando-series-de-precipitacion-mensual","dataUrl":"/capitulo-2-imputando-series-de-precipitacion-mensu.json","internal":true,"protocol":"file","key":"yRMTNq06KZ"}],"key":"LQiQub11v5"}],"key":"rPp0FOOisn"}],"key":"FXpsQOIFmz"}],"key":"DvT9tPscZ0"}],"key":"bHITk2YH3B"},"references":{"cite":{"order":[],"data":{}}},"footer":{"navigation":{"next":{"title":"Capitulo 1: Estado del Arte (Algoritmos Implementados)","url":"/capitulo-1-actividad-1","group":"Series de tiempo"}}},"domain":"http://localhost:3000"}